airflow/providers/alibaba/__init__.py
airflow/providers/alibaba/get_provider_info.py
airflow/providers/alibaba/version_compat.py
airflow/providers/alibaba/cloud/__init__.py
airflow/providers/alibaba/cloud/exceptions.py
airflow/providers/alibaba/cloud/hooks/__init__.py
airflow/providers/alibaba/cloud/hooks/analyticdb_spark.py
airflow/providers/alibaba/cloud/hooks/base_alibaba.py
airflow/providers/alibaba/cloud/hooks/maxcompute.py
airflow/providers/alibaba/cloud/hooks/oss.py
airflow/providers/alibaba/cloud/links/__init__.py
airflow/providers/alibaba/cloud/links/maxcompute.py
airflow/providers/alibaba/cloud/log/__init__.py
airflow/providers/alibaba/cloud/log/oss_task_handler.py
airflow/providers/alibaba/cloud/operators/__init__.py
airflow/providers/alibaba/cloud/operators/analyticdb_spark.py
airflow/providers/alibaba/cloud/operators/maxcompute.py
airflow/providers/alibaba/cloud/operators/oss.py
airflow/providers/alibaba/cloud/sensors/__init__.py
airflow/providers/alibaba/cloud/sensors/analyticdb_spark.py
airflow/providers/alibaba/cloud/sensors/oss_key.py
apache_airflow_providers_alibaba-3.3.3.dist-info/entry_points.txt
apache_airflow_providers_alibaba-3.3.3.dist-info/licenses/LICENSE
apache_airflow_providers_alibaba-3.3.3.dist-info/licenses/NOTICE
apache_airflow_providers_alibaba-3.3.3.dist-info/WHEEL
apache_airflow_providers_alibaba-3.3.3.dist-info/METADATA
apache_airflow_providers_alibaba-3.3.3.dist-info/RECORD
